.gitignore
CHANGES.txt
INSTALL.txt
README.txt
bootstrap.py
buildout.cfg
setup.py
src/sterch/__init__.py
src/sterch.threading.egg-info/PKG-INFO
src/sterch.threading.egg-info/SOURCES.txt
src/sterch.threading.egg-info/dependency_links.txt
src/sterch.threading.egg-info/namespace_packages.txt
src/sterch.threading.egg-info/requires.txt
src/sterch.threading.egg-info/top_level.txt
src/sterch/threading/README.txt
src/sterch/threading/__init__.py
src/sterch/threading/configure.zcml
src/sterch/threading/interfaces.py
src/sterch/threading/meta.zcml
src/sterch/threading/metaconfigure.py
src/sterch/threading/metadirectives.py
src/sterch/threading/tests/__init__.py
src/sterch/threading/tests/test_classes_objects.py
src/sterch/threading/tests/test_condition_directive.py
src/sterch/threading/tests/test_event_directive.py
src/sterch/threading/tests/test_lock_directives.py
src/sterch/threading/tests/test_semaphore_directive.py
src/sterch/threading/tests/test_thread_directive.py
src/sterch/threading/tests/test_timer_directive.py